gpvolve/.DS_Store
gpvolve/__init__.py
gpvolve/__version__.py
gpvolve/fitness.py
gpvolve/fixation.py
gpvolve/flux.py
gpvolve/markovmodel.py
gpvolve/paths.py
gpvolve/utils.py
gpvolve/visualization.py
gpvolve/analysis/pathways.py
gpvolve/cluster/base.py
gpvolve/cluster/from_paths.py
gpvolve/cluster/pcca.py
gpvolve/cluster/utils.py
gpvolve-0.2.0.dist-info/LICENSE
gpvolve-0.2.0.dist-info/METADATA
gpvolve-0.2.0.dist-info/WHEEL
gpvolve-0.2.0.dist-info/top_level.txt
gpvolve-0.2.0.dist-info/RECORD
