Metadata-Version: 2.1
Name: gpvolve
Version: 0.2.0
Summary: A python package for extracting tevolutionary trajectories from genotype-phenotype-maps
Home-page: https://github.com/harmslab/gpvolve
Author: Leander D. Goldbach
Author-email: l.d.goldbach@students.uu.nl
License: MIT
Platform: UNKNOWN
Classifier: License :: OSI Approved :: MIT License
Classifier: Programming Language :: Python
Classifier: Programming Language :: Python :: 3
Classifier: Programming Language :: Python :: 3.6
Classifier: Programming Language :: Python :: Implementation :: CPython
Classifier: Programming Language :: Python :: Implementation :: PyPy
Requires-Python: >=3.6.0
Requires-Dist: numpy
Requires-Dist: cython
Requires-Dist: networkx
Requires-Dist: msmtools
Requires-Dist: gpmap
Requires-Dist: gpgraph
Requires-Dist: matplotlib
